syso_andybonnetto/__init__.py
syso_andybonnetto/syso.py
syso_andybonnetto/sysoproj.py
syso_andybonnetto-0.0.1.dist-info/METADATA
syso_andybonnetto-0.0.1.dist-info/WHEEL
syso_andybonnetto-0.0.1.dist-info/licenses/LICENCE
syso_andybonnetto-0.0.1.dist-info/RECORD
